docs/.gitignore
docs/Makefile
docs/conf.py
docs/index.rst
docs/make.bat
docs/ref/pyskema.rst
pyskema/__init__.py
pyskema/describe.py
pyskema/edit.py
pyskema/misc.py
pyskema/schema.py
pyskema/template.py
pyskema/validate.py
pyskema/visitor.py
pyskema-0.4.4.dist-info/LICENSE
pyskema-0.4.4.dist-info/METADATA
pyskema-0.4.4.dist-info/WHEEL
pyskema-0.4.4.dist-info/top_level.txt
pyskema-0.4.4.dist-info/RECORD
