Metadata-Version: 2.1
Name: pyskema
Version: 0.4.4
Summary: A schema definition module for validation and documentation of structured data.
Author-email: Théo Cavignac <theo.cavignac+dev@gmail.com>
License: Copyright 2023 Théo Cavignac <theo.cavignac+dev@gmail.com>
Project-URL: repository, https://git.sr.ht/~lattay/python-pyskema
Project-URL: documentation, https://pyskema.readthedocs.io
Classifier: License :: OSI Approved :: BSD License
Classifier: Programming Language :: Python :: 3
Classifier: Programming Language :: Python :: 3 :: Only
Requires-Python: >=3.7
License-File: LICENSE
